django_drf_filepond/__init__.py
django_drf_filepond/api.py
django_drf_filepond/apps.py
django_drf_filepond/decorators.py
django_drf_filepond/deprecation.py
django_drf_filepond/django_utils.py
django_drf_filepond/drf_filepond_settings.py
django_drf_filepond/exceptions.py
django_drf_filepond/models.py
django_drf_filepond/parsers.py
django_drf_filepond/renderers.py
django_drf_filepond/storage_utils.py
django_drf_filepond/uploaders.py
django_drf_filepond/urls.py
django_drf_filepond/utils.py
django_drf_filepond/views.py
django_drf_filepond/migrations/0001_initial.py
django_drf_filepond/migrations/0002_add_upload_dir.py
django_drf_filepond/migrations/0003_add_storedupload.py
django_drf_filepond/migrations/0004_tempupload_mods.py
django_drf_filepond/migrations/0005_add_uploaded_by.py
django_drf_filepond/migrations/0006_permupload_mods.py
django_drf_filepond/migrations/0007_altered_stored_upload_file.py
django_drf_filepond/migrations/0008_temporaryuploadchunked.py
django_drf_filepond/migrations/0009_temporaryuploadchunked_offset_utime.py
django_drf_filepond/migrations/0010_temp_chunked_biginteger.py
django_drf_filepond/migrations/__init__.py
django_drf_filepond-0.5.2.dist-info/LICENSE
django_drf_filepond-0.5.2.dist-info/METADATA
django_drf_filepond-0.5.2.dist-info/WHEEL
django_drf_filepond-0.5.2.dist-info/top_level.txt
django_drf_filepond-0.5.2.dist-info/RECORD
