Metadata-Version: 2.1
Name: django-drf-filepond
Version: 0.5.2
Summary: Filepond server app for Django REST Framework
Home-page: https://github.com/ImperialCollegeLondon/django-drf-filepond
Download-URL: https://github.com/ImperialCollegeLondon/django-drf-filepond.git
Author: Jeremy Cohen
Author-email: jeremy.cohen@imperial.ac.uk
License: BSD 3-Clause
Classifier: Operating System :: OS Independent
Classifier: Development Status :: 4 - Beta
Classifier: Environment :: Web Environment
Classifier: Framework :: Django
Classifier: Intended Audience :: Developers
Classifier: License :: OSI Approved :: BSD License
Classifier: Programming Language :: Python :: 2.7
Classifier: Programming Language :: Python :: 3.5
Classifier: Programming Language :: Python :: 3.6
Classifier: Programming Language :: Python :: 3.7
Classifier: Programming Language :: Python :: 3.8
Classifier: Programming Language :: Python :: 3.9
Classifier: Programming Language :: Python :: 3.10
Classifier: Programming Language :: Python :: 3.11
Classifier: Programming Language :: Python :: 3.12
Classifier: Topic :: Software Development :: Libraries :: Python Modules
License-File: LICENSE
Requires-Dist: requests >=2.20.1
Requires-Dist: six >=1.14.0
Requires-Dist: Django <2.0.0,>=1.11.29 ; python_version == "2.7"
Requires-Dist: djangorestframework ==3.9.4 ; python_version == "2.7"
Requires-Dist: shortuuid ==0.5.0 ; python_version == "2.7"
Requires-Dist: django-storages ==1.9.1 ; python_version == "2.7"
Requires-Dist: Django <3.0.0,>=2.2.25 ; python_version == "3.5"
Requires-Dist: Django >=5.2.8 ; python_version >= "3.10"
Requires-Dist: djangorestframework >=3.12.4 ; python_version >= "3.5"
Requires-Dist: shortuuid >=0.5.0 ; python_version >= "3.5"
Requires-Dist: django-storages >=1.9.1 ; python_version >= "3.5"
Requires-Dist: Django <4.0.0,>=3.2.25 ; python_version >= "3.6" and python_version <= "3.7"
Requires-Dist: djangorestframework ==3.14.0 ; python_version >= "3.6" and python_version <= "3.7"
Requires-Dist: djangorestframework >=3.15.2 ; python_version >= "3.8"
Requires-Dist: Django <5.0.0,>=4.2.26 ; python_version >= "3.8" and python_version <= "3.9"
